files_flattener/__init__.py
files_flattener/cli.py
files_flattener/core.py
files_flattener/common/__init__.py
files_flattener/common/logger.py
files_flattener-0.1.2.dist-info/LICENSE
files_flattener-0.1.2.dist-info/METADATA
files_flattener-0.1.2.dist-info/WHEEL
files_flattener-0.1.2.dist-info/entry_points.txt
files_flattener-0.1.2.dist-info/top_level.txt
files_flattener-0.1.2.dist-info/RECORD
