Metadata-Version: 2.1
Name: files-flattener
Version: 0.1.2
Summary: Use files-flattener to flatten your whole structured code project into a single file.
Home-page: https://github.com/sweetbrulee/files-flattener
Author: sweetbrulee
Author-email: sparrowking002@gmail.com
Classifier: Programming Language :: Python :: 3
Classifier: License :: OSI Approved :: MIT License
Classifier: Operating System :: OS Independent
License-File: LICENSE
Requires-Dist: pathspec
Requires-Dist: colorlog
